parviraptor/__init__.py
parviraptor/apps.py
parviraptor/exceptions.py
parviraptor/monitoring.py
parviraptor/urls.py
parviraptor/utils.py
parviraptor/worker.py
parviraptor/management/__init__.py
parviraptor/management/commands/__init__.py
parviraptor/management/commands/clean_old_finished_jobs.py
parviraptor/management/commands/process_queue.py
parviraptor/models/__init__.py
parviraptor/models/abstract.py
parviraptor/templates/parviraptor/open_queue_entries.html
parviraptor/templates/parviraptor/queue_monitoring.html
parviraptor/test/__init__.py
parviraptor/test/case.py
parviraptor/test/factory.py
parviraptor/test/utils.py
parviraptor/test/worker.py
parviraptor/views/__init__.py
parviraptor/views/open_queue_entries.py
parviraptor/views/queue_monitoring.py
parviraptor-3.4.0.dist-info/licenses/LICENSE
tests/__init__.py
tests/models.py
tests/settings.py
tests/test_abstract_job.py
tests/test_factory.py
tests/test_monitoring.py
tests/test_monitoring_endpoint.py
tests/test_open_queue_entries.py
tests/test_parallelity.py
tests/test_queue.py
tests/utils.py
tests/commands/__init__.py
tests/commands/test_clean_old_finished_jobs.py
tests/commands/test_process_queue.py
parviraptor-3.4.0.dist-info/METADATA
parviraptor-3.4.0.dist-info/WHEEL
parviraptor-3.4.0.dist-info/top_level.txt
parviraptor-3.4.0.dist-info/zip-safe
parviraptor-3.4.0.dist-info/RECORD
