Metadata-Version: 2.4
Name: parviraptor
Version: 3.4.0
Summary: Django-based job queue
Home-page: https://github.com/puzzleYOU/parviraptor
Author: puzzleYOU GmbH
License: MIT
Requires-Python: >=3.12
License-File: LICENSE
Requires-Dist: Django
Dynamic: author
Dynamic: description
Dynamic: description-content-type
Dynamic: home-page
Dynamic: license
Dynamic: license-file
Dynamic: requires-dist
Dynamic: requires-python
Dynamic: summary
